dirs_navigator/__about__.py
dirs_navigator/__init__.py
dirs_navigator/navigator.py
fzf_utilities/__init__.py
fzf_utilities/_vim_translator.py
fzf_utilities/ripgrep_to_fzf_filter.py
dirs_navigator-0.0.4.dist-info/METADATA
dirs_navigator-0.0.4.dist-info/WHEEL
dirs_navigator-0.0.4.dist-info/entry_points.txt
dirs_navigator-0.0.4.dist-info/licenses/LICENSE.txt
dirs_navigator-0.0.4.dist-info/RECORD
